uncertainty_metrics/__init__.py
uncertainty_metrics/version.py
uncertainty_metrics/numpy/__init__.py
uncertainty_metrics/numpy/censored_calibration_error.py
uncertainty_metrics/numpy/censored_calibration_error_test.py
uncertainty_metrics/numpy/general_calibration_error.py
uncertainty_metrics/numpy/general_calibration_error_test.py
uncertainty_metrics/numpy/semiparametric_calibration_error.py
uncertainty_metrics/numpy/semiparametric_calibration_error_test.py
uncertainty_metrics/numpy/visualization.py
uncertainty_metrics/tensorflow/__init__.py
uncertainty_metrics/tensorflow/auc.py
uncertainty_metrics/tensorflow/auc_test.py
uncertainty_metrics/tensorflow/calibration.py
uncertainty_metrics/tensorflow/calibration_test.py
uncertainty_metrics/tensorflow/diversity.py
uncertainty_metrics/tensorflow/diversity_test.py
uncertainty_metrics/tensorflow/information_criteria.py
uncertainty_metrics/tensorflow/information_criteria_test.py
uncertainty_metrics/tensorflow/scoring_rules.py
uncertainty_metrics/tensorflow/scoring_rules_test.py
uncertainty_metrics-0.0.81.dist-info/DESCRIPTION.rst
uncertainty_metrics-0.0.81.dist-info/METADATA
uncertainty_metrics-0.0.81.dist-info/RECORD
uncertainty_metrics-0.0.81.dist-info/WHEEL
uncertainty_metrics-0.0.81.dist-info/metadata.json
uncertainty_metrics-0.0.81.dist-info/top_level.txt
